[{"timestamp":"11-11-25 19:00:59","temperature":24.1,"humidity":55,"soil":86},{"timestamp":"11-11-25 19:01:09","temperature":24.1,"humidity":55,"soil":84},{"timestamp":"11-11-25 19:01:19","temperature":24.1,"humidity":55,"soil":84},{"timestamp":"11-11-25 19:01:29","temperature":24.1,"humidity":55,"soil":86},{"timestamp":"11-11-25 19:01:39","temperature":24.1,"humidity":55,"soil":84},{"timestamp":"11-11-25 19:01:49","temperature":24.1,"humidity":55,"soil":86},{"timestamp":"11-11-25 19:01:59","temperature":24.1,"humidity":55,"soil":84},{"timestamp":"11-11-25 19:02:09","temperature":24.1,"humidity":55,"soil":85},{"timestamp":"11-11-25 19:02:19","temperature":24.1,"humidity":55,"soil":84},{"timestamp":"11-11-25 19:02:29","temperature":24.1,"humidity":55,"soil":84},{"timestamp":"11-11-25 19:02:39","temperature":24.1,"humidity":55,"soil":83},{"timestamp":"11-11-25 19:02:49","temperature":24.1,"humidity":54,"soil":87},{"timestamp":"11-11-25 19:02:59","temperature":24.1,"humidity":54,"soil":84},{"timestamp":"11-11-25 19:03:10","temperature":24.1,"humidity":54,"soil":84},{"timestamp":"11-11-25 19:03:20","temperature":24.1,"humidity":54,"soil":85},{"timestamp":"11-11-25 19:03:30","temperature":24.1,"humidity":54,"soil":87},{"timestamp":"11-11-25 19:03:40","temperature":24.1,"humidity":54,"soil":86},{"timestamp":"11-11-25 19:03:50","temperature":24.1,"humidity":54,"soil":85},{"timestamp":"11-11-25 19:04:00","temperature":24.1,"humidity":54,"soil":85},{"timestamp":"11-11-25 19:04:10","temperature":24.1,"humidity":54,"soil":85},{"timestamp":"11-11-25 19:04:20","temperature":24.1,"humidity":54,"soil":85},{"timestamp":"11-11-25 19:04:31","temperature":24.1,"humidity":54,"soil":83},{"timestamp":"11-11-25 19:04:41","temperature":24.1,"humidity":54,"soil":85},{"timestamp":"11-11-25 19:04:51","temperature":24.1,"humidity":54,"soil":85},{"timestamp":"11-11-25 19:05:01","temperature":24.1,"humidity":54,"soil":84},{"timestamp":"11-11-25 19:05:11","temperature":24.1,"humidity":54,"soil":84},{"timestamp":"11-11-25 19:05:21","temperature":24.1,"humidity":54,"soil":84},{"timestamp":"11-11-25 19:05:31","temperature":24.1,"humidity":54,"soil":84},{"timestamp":"11-11-25 19:05:42","temperature":24.1,"humidity":54,"soil":85},{"timestamp":"11-11-25 19:05:52","temperature":24.1,"humidity":54,"soil":87},{"timestamp":"11-11-25 19:06:02","temperature":24.1,"humidity":54,"soil":84},{"timestamp":"11-11-25 19:06:12","temperature":24.1,"humidity":54,"soil":86}]