[{"timestamp":"06-11-25 14:37:15","temperature":24.5,"humidity":43,"soil":0},{"timestamp":"06-11-25 14:37:25","temperature":24.5,"humidity":43,"soil":0},{"timestamp":"06-11-25 14:37:35","temperature":24.5,"humidity":43,"soil":0},{"timestamp":"06-11-25 14:37:45","temperature":24.5,"humidity":43,"soil":0},{"timestamp":"06-11-25 14:37:55","temperature":24.5,"humidity":43,"soil":0},{"timestamp":"06-11-25 14:38:05","temperature":24.5,"humidity":43,"soil":0},{"timestamp":"06-11-25 14:38:15","temperature":24.5,"humidity":43,"soil":0}]